AUTHORS.txt
CHANGES.txt
LICENSE.txt
MANIFEST.in
README.txt
setup.cfg
setup.py
django_templateaddons.egg-info/PKG-INFO
django_templateaddons.egg-info/SOURCES.txt
django_templateaddons.egg-info/dependency_links.txt
django_templateaddons.egg-info/top_level.txt
docs/conf.py
docs/index.txt
docs/install.txt
docs/_build/doctrees/environment.pickle
docs/_build/doctrees/index.doctree
docs/_build/doctrees/install.doctree
docs/_build/doctrees/context_processors/index.doctree
docs/_build/doctrees/developer_tools/index.doctree
docs/_build/doctrees/template_tags/assign.doctree
docs/_build/doctrees/template_tags/counter.doctree
docs/_build/doctrees/template_tags/heading.doctree
docs/_build/doctrees/template_tags/index.doctree
docs/_build/doctrees/template_tags/javascript.doctree
docs/_build/doctrees/template_tags/replace.doctree
docs/_build/html/.buildinfo
docs/_build/html/genindex.html
docs/_build/html/index.html
docs/_build/html/install.html
docs/_build/html/objects.inv
docs/_build/html/search.html
docs/_build/html/searchindex.js
docs/_build/html/_sources/index.txt
docs/_build/html/_sources/install.txt
docs/_build/html/_sources/context_processors/index.txt
docs/_build/html/_sources/developer_tools/index.txt
docs/_build/html/_sources/template_tags/assign.txt
docs/_build/html/_sources/template_tags/counter.txt
docs/_build/html/_sources/template_tags/heading.txt
docs/_build/html/_sources/template_tags/index.txt
docs/_build/html/_sources/template_tags/javascript.txt
docs/_build/html/_sources/template_tags/replace.txt
docs/_build/html/_static/basic.css
docs/_build/html/_static/default.css
docs/_build/html/_static/doctools.js
docs/_build/html/_static/file.png
docs/_build/html/_static/jquery.js
docs/_build/html/_static/minus.png
docs/_build/html/_static/plus.png
docs/_build/html/_static/pygments.css
docs/_build/html/_static/searchtools.js
docs/_build/html/_static/sidebar.js
docs/_build/html/_static/underscore.js
docs/_build/html/context_processors/index.html
docs/_build/html/developer_tools/index.html
docs/_build/html/template_tags/assign.html
docs/_build/html/template_tags/counter.html
docs/_build/html/template_tags/heading.html
