Metadata-Version: 1.0
Name: django-templateaddons
Version: 0.1dev
Summary: A set of tools for use with templates of the Django framework: additional template tags, context processors and utilities for template tag development.
Home-page: http://bitbucket.org/benoitbryon/django-templateaddons/
Author: Benoit Bryon
Author-email: benoit@marmelune.net
License: LICENSE
Platform: UNKNOWN
Classifier: Development Status :: 3 - Alpha
Classifier: License :: OSI Approved :: BSD License
Classifier: Operating System :: OS Independent
Classifier: Framework :: Django
